CHANGES.txt
CONTRIBUTORS.txt
MANIFEST.in
README.txt
collective.wowlichking-configure.zcml
setup.cfg
setup.py
collective/.DS_Store
collective/__init__.py
collective.wowlichking.egg-info/PKG-INFO
collective.wowlichking.egg-info/SOURCES.txt
collective.wowlichking.egg-info/dependency_links.txt
collective.wowlichking.egg-info/entry_points.txt
collective.wowlichking.egg-info/namespace_packages.txt
collective.wowlichking.egg-info/not-zip-safe
collective.wowlichking.egg-info/paster_plugins.txt
collective.wowlichking.egg-info/requires.txt
collective.wowlichking.egg-info/top_level.txt
collective/wowlichking/.DS_Store
collective/wowlichking/__init__.py
collective/wowlichking/configure.zcml
collective/wowlichking/profiles.zcml
collective/wowlichking/setuphandlers.py
collective/wowlichking/skins.zcml
collective/wowlichking/tests.py
collective/wowlichking/version.txt
collective/wowlichking/browser/.DS_Store
collective/wowlichking/browser/__init__.py
collective/wowlichking/browser/configure.zcml
collective/wowlichking/browser/interfaces.py
collective/wowlichking/browser/viewlet.pt
collective/wowlichking/browser/viewlets.py
collective/wowlichking/browser/images/.DS_Store
collective/wowlichking/browser/images/README.txt
collective/wowlichking/browser/images/background.jpg
collective/wowlichking/browser/images/bg.png
collective/wowlichking/browser/images/button.gif
collective/wowlichking/browser/images/footman.png
collective/wowlichking/browser/images/ogre.png
collective/wowlichking/browser/images/plone_powered.gif
collective/wowlichking/browser/scripts/.DS_Store
collective/wowlichking/browser/scripts/jquery-ui-1.7.2.spritely.custom.min.js
collective/wowlichking/browser/scripts/jquery.spritely-0.2.js
collective/wowlichking/browser/stylesheets/README.txt
collective/wowlichking/browser/stylesheets/main.css
collective/wowlichking/browser/templates/colophon.pt
collective/wowlichking/browser/templates/footer.pt
collective/wowlichking/locales/.DS_Store
collective/wowlichking/locales/README.txt
collective/wowlichking/profiles/default/collective.wowlichking_various.txt
collective/wowlichking/profiles/default/cssregistry.xml
collective/wowlichking/profiles/default/jsregistry.xml
collective/wowlichking/profiles/default/metadata.xml
collective/wowlichking/profiles/default/skins.xml
collective/wowlichking/profiles/default/viewlets.xml
collective/wowlichking/skins/.DS_Store
