Metadata-Version: 1.0
Name: collective.wowlichking
Version: 0.5
Summary: An installable WoW theme for Pone 3
Home-page: http://code.google.com/p/collectivewowlichking/
Author: Marc Goetz
Author-email: goetz.marc@googlemail.com
License: GPL
Keywords: web zope plone theme wow warcraft lich king
Platform: UNKNOWN
Classifier: Framework :: Plone
Classifier: Programming Language :: Python
